pytimecamp/__init__.py
pytimecamp-0.1.12.dist-info/DESCRIPTION.rst
pytimecamp-0.1.12.dist-info/METADATA
pytimecamp-0.1.12.dist-info/RECORD
pytimecamp-0.1.12.dist-info/WHEEL
pytimecamp-0.1.12.dist-info/metadata.json
pytimecamp-0.1.12.dist-info/top_level.txt
