Metadata-Version: 2.0
Name: pytimecamp
Version: 0.1.12
Summary: A wrapper around the Timecamp API.
Home-page: https://pythonhosted.org/pytimecamp/
Author: agiletekengineering
Author-email: london@agiletek.co.uk
License: MIT
Platform: UNKNOWN
Classifier: Development Status :: 4 - Beta
Classifier: Programming Language :: Python :: 3.6
Requires-Dist: requests
Requires-Dist: python-dateutil
